LICENSE.txt
setup.py
MasterYounes.egg-info/PKG-INFO
MasterYounes.egg-info/SOURCES.txt
MasterYounes.egg-info/dependency_links.txt
MasterYounes.egg-info/top_level.txt
code/__init__.py